vaulttool/__init__.py
vaulttool/__main__.py
vaulttool/cli.py
vaulttool/config.py
vaulttool/core.py
vaulttool/tests/conftest.py
vaulttool/tests/test_checksum_trigger.py
vaulttool/tests/test_config.py
vaulttool/tests/test_core.py
vaulttool/tests/test_decrypt_missing_sources.py
vaulttool/tests/test_env_config.py
vaulttool/tests/test_error_aggregation.py
vaulttool/tests/test_gitignore.py
vaulttool/tests/test_key_file_validation.py
vaulttool/tests/test_main_integration.py
vaulttool/tests/test_priority3_fixes.py
vaulttool/tests/test_security_and_edge_cases.py
vaulttool/tests/test_suffix_fallback.py
vaulttool/tests/test_utils.py
vaulttool/utils.py
vaulttool-2.0.1.dist-info/LICENSE
vaulttool-2.0.1.dist-info/METADATA
vaulttool-2.0.1.dist-info/WHEEL
vaulttool-2.0.1.dist-info/entry_points.txt
vaulttool-2.0.1.dist-info/RECORD
