Metadata-Version: 2.1
Name: vaulttool
Version: 2.0.1
Summary: Secure file encryption for secrets/configs
Home-page: https://github.com/yourusername/vaulttool
License: Apache-2
Author: Josef Fuchs
Requires-Python: >=3.10
Classifier: License :: Other/Proprietary License
Classifier: Programming Language :: Python :: 3
Classifier: Programming Language :: Python :: 3.10
Classifier: Programming Language :: Python :: 3.11
Classifier: Programming Language :: Python :: 3.12
Classifier: Programming Language :: Python :: 3.13
Requires-Dist: cryptography
Requires-Dist: pytest (>=8.4.2,<9.0.0)
Requires-Dist: pyyaml
Requires-Dist: typer
